lerler/__init__.py
lerler/main.py
lerler-0.3.dist-info/METADATA
lerler-0.3.dist-info/WHEEL
lerler-0.3.dist-info/entry_points.txt
lerler-0.3.dist-info/top_level.txt
lerler-0.3.dist-info/RECORD
