Metadata-Version: 2.4
Name: lerler
Version: 0.3
Requires-Dist: numpy>=1.0.0
Dynamic: description-content-type
Dynamic: requires-dist
